abctoolkit/__init__.py
abctoolkit/abc2xml.py
abctoolkit/batch_transpose.py
abctoolkit/check.py
abctoolkit/convert.py
abctoolkit/data.py
abctoolkit/duration.py
abctoolkit/rotate.py
abctoolkit/transpose.py
abctoolkit/utils.py
abctoolkit/xml2abc.py
abctoolkit/convert/1_batch_convert2xml.py
abctoolkit/convert/2_batch_convert2abc.py
abctoolkit-0.0.5.dist-info/METADATA
abctoolkit-0.0.5.dist-info/WHEEL
abctoolkit-0.0.5.dist-info/RECORD
