Metadata-Version: 2.3
Name: abctoolkit
Version: 0.0.5
Summary: A Toolkit for dealing with ABC Notation scores in Music Information Retrieval.
Author-email: Alexis Wang <alexis_wang@mail.ccom.edu.cn>, Sander Wood <shangda@mail.ccom.edu.cn>
Classifier: License :: OSI Approved :: MIT License
Classifier: Operating System :: OS Independent
Classifier: Programming Language :: Python :: 3
Requires-Python: >=3.7
Requires-Dist: jellyfish>=1.0.0
Requires-Dist: rapidfuzz>=3.9.1
Requires-Dist: tqdm>=4.66.1
Requires-Dist: unidecode>=1.3.6
